Metadata-Version: 2.1
Name: kmerslib
Version: 1.0.11
Summary: An example project showing how to build a pip-installable Python package that invokes custom CUDA/C++ code.
Home-page: UNKNOWN
Author: Isaias May Canche
Author-email: isaias.mc@chetumal.tecnm.mx
License: UNKNOWN
Platform: UNKNOWN
